openslide_bin-4.0.0.11.dist-info/METADATA
openslide_bin-4.0.0.11.dist-info/RECORD
openslide_bin-4.0.0.11.dist-info/WHEEL
openslide_bin-4.0.0.11.dist-info/licenses/COPYING.LESSER
openslide_bin-4.0.0.11.dist-info/licenses/licenses/OpenJPEG/LICENSE
openslide_bin-4.0.0.11.dist-info/licenses/licenses/OpenSlide/COPYING.LESSER
openslide_bin-4.0.0.11.dist-info/licenses/licenses/PCRE2/LICENCE.md
openslide_bin-4.0.0.11.dist-info/licenses/licenses/SQLite/PUBLIC-DOMAIN.txt
openslide_bin-4.0.0.11.dist-info/licenses/licenses/cairo/COPYING
openslide_bin-4.0.0.11.dist-info/licenses/licenses/cairo/COPYING-LGPL-2.1
openslide_bin-4.0.0.11.dist-info/licenses/licenses/cairo/COPYING-MPL-1.1
openslide_bin-4.0.0.11.dist-info/licenses/licenses/gdk-pixbuf/COPYING
openslide_bin-4.0.0.11.dist-info/licenses/licenses/glib/COPYING
openslide_bin-4.0.0.11.dist-info/licenses/licenses/libdicom/LICENSE
openslide_bin-4.0.0.11.dist-info/licenses/licenses/libffi/LICENSE
openslide_bin-4.0.0.11.dist-info/licenses/licenses/libjpeg-turbo/LICENSE.md
openslide_bin-4.0.0.11.dist-info/licenses/licenses/libjpeg-turbo/README.ijg
openslide_bin-4.0.0.11.dist-info/licenses/licenses/libpng/LICENSE
openslide_bin-4.0.0.11.dist-info/licenses/licenses/libtiff/LICENSE.md
openslide_bin-4.0.0.11.dist-info/licenses/licenses/libxml2/Copyright
openslide_bin-4.0.0.11.dist-info/licenses/licenses/pixman/COPYING
openslide_bin-4.0.0.11.dist-info/licenses/licenses/proxy-libintl/COPYING
openslide_bin-4.0.0.11.dist-info/licenses/licenses/uthash/LICENSE
openslide_bin-4.0.0.11.dist-info/licenses/licenses/zlib-ng/LICENSE.md
openslide_bin/__init__.py
openslide_bin/libopenslide-1.dll
openslide_bin/py.typed
