Metadata-Version: 2.4
Name: openslide-bin
Version: 4.0.0.11
Maintainer-Email: OpenSlide project <openslide-users@lists.andrew.cmu.edu>
Summary: Binary build of OpenSlide
License-Expression: LGPL-2.1-only AND blessing AND BSD-1-Clause AND BSD-2-Clause AND BSD-3-Clause AND BSD-3-Clause WITH PCRE2-exception AND BSD-4.3TAHOE AND IJG AND LGPL-2.0-or-later AND (LGPL-2.1-only OR MPL-1.1) AND LGPL-2.1-or-later AND libpng-2.0 AND libtiff AND MIT AND Zlib
License-File: COPYING.LESSER
License-File: licenses/cairo/COPYING
License-File: licenses/cairo/COPYING-LGPL-2.1
License-File: licenses/cairo/COPYING-MPL-1.1
License-File: licenses/gdk-pixbuf/COPYING
License-File: licenses/glib/COPYING
License-File: licenses/libdicom/LICENSE
License-File: licenses/libffi/LICENSE
License-File: licenses/libjpeg-turbo/LICENSE.md
License-File: licenses/libjpeg-turbo/README.ijg
License-File: licenses/libpng/LICENSE
License-File: licenses/libtiff/LICENSE.md
License-File: licenses/libxml2/Copyright
License-File: licenses/OpenJPEG/LICENSE
License-File: licenses/OpenSlide/COPYING.LESSER
License-File: licenses/PCRE2/LICENCE.md
License-File: licenses/pixman/COPYING
License-File: licenses/proxy-libintl/COPYING
License-File: licenses/SQLite/PUBLIC-DOMAIN.txt
License-File: licenses/uthash/LICENSE
License-File: licenses/zlib-ng/LICENSE.md
Keywords: OpenSlide,whole-slide image,virtual slide,library
Classifier: Development Status :: 5 - Production/Stable
Classifier: Intended Audience :: Developers
Classifier: Intended Audience :: Healthcare Industry
Classifier: Intended Audience :: Science/Research
Classifier: Operating System :: MacOS :: MacOS X
Classifier: Operating System :: Microsoft :: Windows
Classifier: Operating System :: POSIX :: Linux
Classifier: Programming Language :: Python
Classifier: Programming Language :: Python :: 3
Classifier: Programming Language :: Python :: 3.9
Classifier: Programming Language :: Python :: 3.10
Classifier: Programming Language :: Python :: 3.11
Classifier: Programming Language :: Python :: 3.12
Classifier: Programming Language :: Python :: 3.13
Classifier: Programming Language :: Python :: 3.14
Classifier: Topic :: Scientific/Engineering :: Bio-Informatics
Classifier: Typing :: Typed
Requires-Python: >= 3.9
Home-page: https://openslide.org/
Project-URL: Release notes, https://github.com/openslide/openslide-bin/releases
Project-URL: Repository, https://github.com/openslide/openslide-bin
